odoo10_addon_stock_picking_back2draft-10.0.1.0.0.99.dev3-py3.8-nspkg.pth
odoo/addons/stock_picking_back2draft/README.rst
odoo/addons/stock_picking_back2draft/__init__.py
odoo/addons/stock_picking_back2draft/__manifest__.py
odoo/addons/stock_picking_back2draft/i18n/ca.po
odoo/addons/stock_picking_back2draft/i18n/de.po
odoo/addons/stock_picking_back2draft/i18n/es.po
odoo/addons/stock_picking_back2draft/i18n/es_AR.po
odoo/addons/stock_picking_back2draft/i18n/es_MX.po
odoo/addons/stock_picking_back2draft/i18n/fi.po
odoo/addons/stock_picking_back2draft/i18n/fr.po
odoo/addons/stock_picking_back2draft/i18n/hr.po
odoo/addons/stock_picking_back2draft/i18n/it.po
odoo/addons/stock_picking_back2draft/i18n/pt.po
odoo/addons/stock_picking_back2draft/i18n/pt_BR.po
odoo/addons/stock_picking_back2draft/i18n/sl.po
odoo/addons/stock_picking_back2draft/i18n/stock_picking_back2draft.pot
odoo/addons/stock_picking_back2draft/i18n/tr.po
odoo/addons/stock_picking_back2draft/i18n/tr_TR.po
odoo/addons/stock_picking_back2draft/images/picking.png
odoo/addons/stock_picking_back2draft/models/__init__.py
odoo/addons/stock_picking_back2draft/models/stock.py
odoo/addons/stock_picking_back2draft/static/description/icon.png
odoo/addons/stock_picking_back2draft/tests/__init__.py
odoo/addons/stock_picking_back2draft/tests/test_picking.py
odoo/addons/stock_picking_back2draft/views/picking_view.xml
odoo10_addon_stock_picking_back2draft-10.0.1.0.0.99.dev3.dist-info/METADATA
odoo10_addon_stock_picking_back2draft-10.0.1.0.0.99.dev3.dist-info/WHEEL
odoo10_addon_stock_picking_back2draft-10.0.1.0.0.99.dev3.dist-info/namespace_packages.txt
odoo10_addon_stock_picking_back2draft-10.0.1.0.0.99.dev3.dist-info/top_level.txt
odoo10_addon_stock_picking_back2draft-10.0.1.0.0.99.dev3.dist-info/RECORD
